orange3_data_helpers-0.2.4.dist-info/licenses/LICENSE
orangecontrib/__init__.py
orangecontrib/datahelpers/__init__.py
orangecontrib/datahelpers/utils/driver_installer.py
orangecontrib/datahelpers/widgets/__init__.py
orangecontrib/datahelpers/widgets/ow_data_overview.py
orangecontrib/datahelpers/widgets/ow_data_selected.py
orangecontrib/datahelpers/widgets/ow_data_structure.py
orangecontrib/datahelpers/widgets/ow_db_query.py
orangecontrib/datahelpers/widgets/ow_db_restore.py
orangecontrib/datahelpers/widgets/ow_db_type_inspector.py
orangecontrib/datahelpers/widgets/ow_join_data.py
orangecontrib/datahelpers/widgets/ow_query_loader.py
orangecontrib/datahelpers/widgets/ow_query_table.py
orangecontrib/datahelpers/widgets/ow_save_big.py
orangecontrib/datahelpers/widgets/ow_table_pattern_browser.py
orangecontrib/datahelpers/widgets/icons/addon_icon.png
orangecontrib/datahelpers/widgets/icons/ai_insight.png
orangecontrib/datahelpers/widgets/icons/data_overview.png
orangecontrib/datahelpers/widgets/icons/db_query.png
orangecontrib/datahelpers/widgets/icons/get_data_api.png
orangecontrib/datahelpers/widgets/icons/query_loader.png
orangecontrib/datahelpers/widgets/icons/save_data.png
orangecontrib/datahelpers/widgets/icons/select_row.png
orangecontrib/datahelpers/widgets/icons/table_structure.png
orange3_data_helpers-0.2.4.dist-info/METADATA
orange3_data_helpers-0.2.4.dist-info/WHEEL
orange3_data_helpers-0.2.4.dist-info/entry_points.txt
orange3_data_helpers-0.2.4.dist-info/top_level.txt
orange3_data_helpers-0.2.4.dist-info/RECORD
